spryx_iam/__init__.py
spryx_iam/auth_application.py
spryx_iam/client.py
spryx_iam/resources/__init__.py
spryx_iam/resources/organizations.py
spryx_iam/resources/plans.py
spryx_iam/types/__init__.py
spryx_iam/types/organization.py
spryx_iam/types/plan.py
spryx_iam-0.1.5.dist-info/LICENSE
spryx_iam-0.1.5.dist-info/METADATA
spryx_iam-0.1.5.dist-info/WHEEL
spryx_iam-0.1.5.dist-info/RECORD
