Metadata-Version: 2.3
Name: spryx-iam
Version: 0.1.5
Summary: 
Author: Pedro Cantidio
Author-email: ppcantidio@gmail.com
Requires-Python: >=3.11
Classifier: Programming Language :: Python :: 3
Classifier: Programming Language :: Python :: 3.11
Classifier: Programming Language :: Python :: 3.12
Classifier: Programming Language :: Python :: 3.13
Requires-Dist: spryx-http (>=0.1.7)
